wwpdb/__init__.py
wwpdb/utils/__init__.py
wwpdb/utils/config/ConfigInfo.py
wwpdb/utils/config/ConfigInfoApp.py
wwpdb/utils/config/ConfigInfoData.py
wwpdb/utils/config/ConfigInfoDataSet.py
wwpdb/utils/config/ConfigInfoDataSetExec.py
wwpdb/utils/config/ConfigInfoFile.py
wwpdb/utils/config/ConfigInfoFileExec.py
wwpdb/utils/config/ConfigInfoGroupDataSet.py
wwpdb/utils/config/ConfigInfoShellExec.py
wwpdb/utils/config/ConfigInfoSiteAccess.py
wwpdb/utils/config/ProjectVersionInfo.py
wwpdb/utils/config/__init__.py
wwpdb_utils_config-0.53.0.dist-info/METADATA
wwpdb_utils_config-0.53.0.dist-info/WHEEL
wwpdb_utils_config-0.53.0.dist-info/entry_points.txt
wwpdb_utils_config-0.53.0.dist-info/licenses/LICENSE
wwpdb_utils_config-0.53.0.dist-info/RECORD
