Metadata-Version: 2.4
Name: wwpdb.utils.config
Version: 0.53.0
Summary: wwPDB Python Configuration Parsing
Project-URL: Homepage, https://github.com/rcsb/py-wwpdb_utils_config
Author-email: Ezra Peisach <ezra.peisach@rcsb.org>
License-Expression: Apache-2.0
License-File: LICENSE
Classifier: Development Status :: 3 - Alpha
Classifier: Intended Audience :: Developers
Classifier: License :: OSI Approved :: Apache Software License
Classifier: Natural Language :: English
Classifier: Programming Language :: Python
Classifier: Programming Language :: Python :: 2.7
Classifier: Programming Language :: Python :: 3
Classifier: Programming Language :: Python :: 3.6
Classifier: Programming Language :: Python :: 3.7
Requires-Python: >=2.7
Requires-Dist: oslo-concurrency
Requires-Dist: python-dateutil
